check_params_by_swagger/__init__.py
check_params_by_swagger/check.py
check_params_by_swagger/expected_code.py
check_params_by_swagger/log_file.py
check_params_by_swagger/swagger_parser.py
check_params_by_swagger/util.py
check_params_by_swagger-1.0.0.dist-info/LICENSE.txt
check_params_by_swagger-1.0.0.dist-info/METADATA
check_params_by_swagger-1.0.0.dist-info/WHEEL
check_params_by_swagger-1.0.0.dist-info/top_level.txt
check_params_by_swagger-1.0.0.dist-info/RECORD
