Metadata-Version: 2.1
Name: check-params-by-swagger
Version: 1.0.0
Summary: check param by swagger
Home-page: 
Author: Qredsun
Author-email: 1410672725@qq.com
Classifier: Programming Language :: Python :: 3
Classifier: License :: OSI Approved :: MIT License
Classifier: Operating System :: OS Independent
Requires-Python: >=3.7
License-File: LICENSE.txt
